Obsidian_Snippeter/CLI.py
Obsidian_Snippeter/GUI.py
Obsidian_Snippeter/__init__.py
Obsidian_Snippeter/src/__init__.py
Obsidian_Snippeter/src/environment.py
Obsidian_Snippeter/src/github_action.py
Obsidian_Snippeter/src/gui_bin/folder.png
Obsidian_Snippeter/src/gui_bin/hand.ico
Obsidian_Snippeter/src/gui_bin/hand.png
Obsidian_Snippet_Manager-2.3.2.dist-info/LICENSE
Obsidian_Snippet_Manager-2.3.2.dist-info/METADATA
Obsidian_Snippet_Manager-2.3.2.dist-info/WHEEL
Obsidian_Snippet_Manager-2.3.2.dist-info/entry_points.txt
Obsidian_Snippet_Manager-2.3.2.dist-info/top_level.txt
Obsidian_Snippet_Manager-2.3.2.dist-info/RECORD
