Metadata-Version: 2.1
Name: Obsidian-Snippet-Manager
Version: 2.3.2
Summary: A script to magically update your obsidian snippets hosted on github.
Home-page: https://github.com/Mara-Li/Obsidian-Snippet-Manager
Author: Mara-Li
Author-email: mara_li@icloud.com
License: AGPL
Keywords: Obsidian,Obsidian.md,css,update,manager,obsidian snippet manager,snippets,snippet
Platform: UNKNOWN
Classifier: Natural Language :: English
Classifier: License :: OSI Approved :: GNU Affero General Public License v3 or later (AGPLv3+)
Classifier: Programming Language :: Python :: 3
Classifier: Programming Language :: Python :: 3.6
Classifier: Programming Language :: Python :: 3.7
Classifier: Programming Language :: Python :: 3.8
Classifier: Programming Language :: Python :: 3.9
Requires-Python: >=3.7
License-File: LICENSE
Requires-Dist: rich (==11.2.0)
Requires-Dist: python-dotenv (~=0.19.2)
Requires-Dist: setuptools (==60.8.2)
Requires-Dist: PyYAML (~=6.0)
Requires-Dist: ttkthemes
Requires-Dist: Pillow (~=9.0.1)
Requires-Dist: GitPython
Requires-Dist: validators
